acdh_obj2xml_pyutils/__init__.py
acdh_obj2xml_pyutils-0.0.7.dist-info/LICENSE
acdh_obj2xml_pyutils-0.0.7.dist-info/METADATA
acdh_obj2xml_pyutils-0.0.7.dist-info/WHEEL
acdh_obj2xml_pyutils-0.0.7.dist-info/top_level.txt
acdh_obj2xml_pyutils-0.0.7.dist-info/RECORD
