Metadata-Version: 2.1
Name: acdh_obj2xml_pyutils
Version: 0.0.7
Summary: Utility functions to serialize xml from object
Home-page: https://github.com/acdh-oeaw/acdh-obj2xml-pyutils
Author: Daniel Elsner
Author-email: daniel.elsner@oeaw.ac.at
License: MIT license
Classifier: Intended Audience :: Developers
Classifier: License :: OSI Approved :: MIT License
Classifier: Natural Language :: English
Requires-Python: >=3.8
License-File: LICENSE
Requires-Dist: lxml
Requires-Dist: jinja2
